setup.cfg
setup.py
hwinfo/__init__.py
hwinfo/host/__init__.py
hwinfo/host/cpuinfo.py
hwinfo/host/dmidecode.py
hwinfo/pci/__init__.py
hwinfo/pci/biosdevname.py
hwinfo/pci/lspci.py
hwinfo/tools/__init__.py
hwinfo/tools/inspector.py
hwinfo/util/__init__.py
python_hwinfo.egg-info/PKG-INFO
python_hwinfo.egg-info/SOURCES.txt
python_hwinfo.egg-info/dependency_links.txt
python_hwinfo.egg-info/entry_points.txt
python_hwinfo.egg-info/requires.txt
python_hwinfo.egg-info/top_level.txt