Metadata-Version: 1.1
Name: python-hwinfo
Version: 0.1.4
Summary: Library for parsing hardware info on Linux OSes.
Home-page: https://github.com/rdobson/python-hwinfo
Author: Rob Dobson
Author-email: rob@rdobson.co.uk
License: UNKNOWN
Download-URL: https://github.com/rdobson/python-hwinfo/tarball/0.1.4
Platform: UNKNOWN
